{"Event": {"@xmlns": "http://schemas.microsoft.com/win/2004/08/events/event", "System": {"Provider": {"@Name": "Microsoft-Windows-Sysmon", "@Guid": "{5770385F-C22A-43E0-BF4C-06F5698FFBD9}"}, "EventID": "8", "EventName": "CreateRemoteThread", "EventDescription": "The CreateRemoteThread event detects when a process creates a thread in another process. This technique is used by malware to inject code and hide in other processes. The event indicates the source and target process. It gives information on the code that will be run in the new thread: StartAddress, StartModule and StartFunction.", "Version": "5", "Level": "4", "Task": "8", "Opcode": "0", "Keywords": "0x8000000000000000", "TimeCreated": {"@SystemTime": "2023-04-16T10:20:30.123456Z"}, "EventRecordID": "123456", "Correlation": null, "Execution": {"@ProcessID": "4", "@ThreadID": "80"}, "Channel": "Microsoft-Windows-Sysmon/Operational", "Computer": "DESKTOP-EXAMPLE", "Security": {"@UserID": "S-1-5-18"}}, "EventData": {"Data": [{"@Name": "RuleName", "#text": "-"}, {"@Name": "UtcTime", "#text": "2023-04-16 10:20:30.123"}, {"@Name": "SourceProcessGUID", "#text": "{A1B2C3D4-E5F6-47A8-89AB-1C2D3E4F5G6H}"}, {"@Name": "SourceProcessId", "#text": "1234"}, {"@Name": "SourceImage", "#text": "C:\\Windows\\System32\\example.exe"}, {"@Name": "TargetProcessGUID", "#text": "{F1E2D3C4-B5A6-49C8-D9E1-0F2A3B4C5D6E}"}, {"@Name": "TargetProcessId", "#text": "5678"}, {"@Name": "TargetImage", "#text": "C:\\Windows\\System32\\example-target.exe"}, {"@Name": "NewThreadId", "#text": "999"}, {"@Name": "StartAddress", "#text": "0x1234567890ABCDEF"}, {"@Name": "StartModule", "#text": "C:\\Windows\\System32\\example-target.dll"}, {"@Name": "StartFunction", "#text": "example_function"}]}}}